rss_downloader/__init__.py
rss_downloader/app.py
rss_downloader/config.py
rss_downloader/database.py
rss_downloader/downloaders.py
rss_downloader/logger.py
rss_downloader/main.py
rss_downloader/models.py
rss_downloader/parser.py
rss_downloader/services.py
rss_downloader/static/css/input.css
rss_downloader/static/css/output.css
rss_downloader/templates/base.html
rss_downloader/templates/config.html
rss_downloader/templates/error.html
rss_downloader/templates/index.html
rss_downloader/web.py
rss_downloader/webhook.py
rss_downloader-0.3.0.dist-info/licenses/LICENSE
rss_downloader-0.3.0.dist-info/WHEEL
rss_downloader-0.3.0.dist-info/entry_points.txt
rss_downloader-0.3.0.dist-info/METADATA
rss_downloader-0.3.0.dist-info/RECORD
