Metadata-Version: 2.4
Name: rss-downloader
Version: 0.3.0
Summary: A Simple RSS Download Manager
Keywords: rss,downloader,aria2,qbittorrent,automation,anime
Author: GrassSand
Author-email: GrassSand <grasssand@users.noreply.github.com>
License-Expression: MIT
License-File: LICENSE
Classifier: Development Status :: 5 - Production/Stable
Classifier: Environment :: Console
Classifier: Framework :: FastAPI
Classifier: Intended Audience :: End Users/Desktop
Classifier: License :: OSI Approved :: MIT License
Classifier: Operating System :: OS Independent
Classifier: Programming Language :: Python :: 3 :: Only
Classifier: Programming Language :: Python :: 3.10
Classifier: Programming Language :: Python :: 3.11
Classifier: Programming Language :: Python :: 3.12
Classifier: Programming Language :: Python :: 3.13
Classifier: Programming Language :: Python :: 3.14
Classifier: Topic :: Internet
Classifier: Topic :: Utilities
Requires-Dist: aiosqlite>=0.21.0
Requires-Dist: anyio>=4.10.0
Requires-Dist: fastapi[standard]>=0.116.1
Requires-Dist: feedparser>=6.0.11
Requires-Dist: httpx>=0.28.1
Requires-Dist: loguru>=0.7.3
Requires-Dist: pydantic>=2.11.7
Requires-Dist: pyyaml>=6.0.2
Requires-Python: >=3.10
Project-URL: Bug Tracker, https://github.com/grasssand/rss-downloader/issues
Project-URL: Homepage, https://github.com/grasssand/rss-downloader
Project-URL: Repository, https://github.com/grasssand/rss-downloader
